Workbook

Sheet Dashboard & Métricas
C2: Métricas Calidad QA
C4: Metricas de Ejecución
D9: =IF(AND($E$14=0, $E$10>0, $D$9<>""), $D$9, "Sprint: (" & TEXT(TODAY() - WEEKDAY(TODAY(), 2) + 1, "dd/mm/yyyy") & " - " & TEXT(TODAY() - WEEKDAY(TODAY(), 2) + 5, "dd/mm/yyyy") & ")") -> #REF!
D10: Total de Casos Sprint | E10: =$D$22+$H$22 -> 65
D11: Total de Casos Pasados | E11: =$D$29+$H$29 -> 0
D12: Total de Casos Fallados | E12: =$D$30+$H$30 -> 0
D13: Total de Casos Bloqueados | E13: =$D$31+$H$31 -> 0
D14: Total de Casos sin Ejecutar | E14: =E10-E11-E12 -> 65
D15: *La fecha sprint considera valores del dia Actual
C22: Total de Casos Manuales | D22: =SUM('Matriz Casos de Prueba Puebla'!D84) -> 65
C23: Casos Manuales Ejecutados | D23: =SUM('Matriz Casos de Prueba Puebla'!D88) -> 0
C24: Porcentaje de Paso (Pass Rate) | D24: =D29/D23 -> #DIV/0!
C27: Resultado de Ejecución de Pruebas Manuales
C28: Estado | D28: Cantidad
C29: Pasó | D29: ='Matriz Casos de Prueba Puebla'!D85 -> 0
C30: Falló | D30: ='Matriz Casos de Prueba Puebla'!D86 -> 0
C31: Bloqueado | D31: ='Matriz Casos de Prueba Puebla'!D87 -> 0
C32: Sin Ejecutar | D32: =$D$22-$D$23 -> 65

Sheet Matriz Casos de Prueba Puebla
E3: Diseño y Ejecución de Casos de Prueba
E5: Nombre del Proyecto: | F5: Puebla - Rompefilas (Terminal T6)
E6: Creado por: | F6: QA
E7: Fecha: | F7: =IF(OR($D88<$D84, $E88<$E84), TODAY(), IF(AND(F7<>"", F7<>0), F7, TODAY())) -> 46307
C9: Casos de Prueba | N9: Ejecución
C10: Producto | D10: Módulo | E10: Escenario | F10: ID Caso | G10: Nombre del Caso de prueba | H10: Descripción del Caso de Prueba | I10: Pre condiciónes | J10: Pasos de Ejecución | K10: Resultado Esperado | L10: Prioridad | M10: Estatus Automatización | N10: Aplica | O10: Ambiente | P10: Tipo de Ejecución | Q10: Tipo de Prueba | R10: Fecha Planeada | S10: Fecha de Ejecución | T10: Estatus | U10: Evidencia | V10: Observaciones
C11: Selecciona... | D11: General | E11: UI | F11: CP-GU-POS-001 | G11: Integración versión en footer | H11: Validar que en el pie de la aplicación, se visualice la versión usada | I11: 1. Usuario registrado 2. Versión generada | J11: 1. Abrir lla app instalada 2. Confirmar la versión correcta | K11: Se cuenta con el footer con la versión correcta | L11: Alta | M11: Sin automatizar | N11: No | O11: QA | P11: Manual | Q11: UI | S11: =IF($T11<>"Sin Ejecutar", IF($S11="", TODAY(), $S11), "") | T11: Sin Ejecutar
C12: Rompefilas | D12: General | E12: Visualización | F12: CP-ID-ROM-001 | G12: Consulta con referencia de 16 dígitos válida (captura manual en T6) | H12: Validar: Consulta con referencia de 16 dígitos válida (captura manual en T6) | I12: App RompeFilas abierta en la T6. Contribuyente en fila con recibo que contiene referencia de 16 dígitos. Datos de prueba: Referencia: PU - 5001 | J12: 1. Tocar 'Toque para iniciar'. 2. Capturar los 16 dígitos con el teclado numérico en pantalla de la T6. 3. Presionar 'Consultar adeudos'. | K12: El teclado numérico se muestra completo sin ocultar el campo ni el botón 'Consultar adeudos'. El sistema muestra P2 con la lista de adeudos del contribuyente. | L12: Alta | M12: Sin automatizar | N12: No | O12: QA | P12: Manual | Q12: Funcional | S12: =IF($T12<>"Sin Ejecutar", IF($S12="", TODAY(), $S12), "") | T12: Sin Ejecutar
C13: Rompefilas | D13: General | E13: Visualización | F13: CP-ID-ROM-002 | G13: Consulta escaneando código de barras/QR con el lector/cámara de la T6 | H13: Validar: Consulta escaneando código de barras/QR con el lector/cámara de la T6 | I13: App en P1. Recibo físico con código de barras/QR legible. Luz ambiente normal. Datos de prueba: QR / Código de barras del recibo | J13: 1. Tocar 'Toque para iniciar'. 2. Tocar 'Escanear' (si aplica) y apuntar el lector/cámara de la T6 al recibo. 3. Esperar lectura automática. | K13: La T6 captura la referencia en ≤ 3 s, emite confirmación (sonido/vibración) y avanza a P2 sin captura manual. | L13: Alta | M13: Sin automatizar | N13: No | O13: QA | P13: Manual | Q13: Funcional | S13: =IF($T13<>"Sin Ejecutar", IF($S13="", TODAY(), $S13), "") | T13: Sin Ejecutar
C14: Rompefilas | D14: General | E14: Bloqueos | F14: CP-ID-ROM-003 | G14: Referencia con menos de 16 dígitos | H14: Validar: Referencia con menos de 16 dígitos | I14: App en P1 (identificación). Datos de prueba: 1234567890 (10 dígitos) | J14: 1. Capturar 10 dígitos. 2. Presionar 'Consultar adeudos'. | K14: Se muestra el mensaje 'No se encontraron adeudos para esta referencia' (o validación de longitud) completo y legible en la pantalla de la T6. | L14: Media | M14: Sin automatizar | N14: No | O14: QA | P14: Manual | Q14: Funcional | S14: =IF($T14<>"Sin Ejecutar", IF($S14="", TODAY(), $S14), "") | T14: Sin Ejecutar
C15: Rompefilas | D15: General | E15: Bloqueos | F15: CP-ID-ROM-004 | G15: Referencia de 16 dígitos que no existe en el padrón | H15: Validar: Referencia de 16 dígitos que no existe en el padrón | I15: App en P1 (identificación). Datos de prueba: 0000000000000000 | J15: 1. Capturar 16 dígitos que no corresponden a ningún contribuyente. 2. Presionar 'Consultar adeudos'. | K15: Se muestra el mensaje 'No se encontraron adeudos para esta referencia'. La app permanece en P1 lista para un nuevo intento. | L15: Media | M15: Sin automatizar | N15: No | O15: QA | P15: Manual | Q15: Funcional | S15: =IF($T15<>"Sin Ejecutar", IF($S15="", TODAY(), $S15), "") | T15: Sin Ejecutar
C16: Rompefilas | D16: General | E16: Bloqueos | F16: CP-ID-ROM-005 | G16: Código de barras/QR ilegible o dañado | H16: Validar: Código de barras/QR ilegible o dañado | I16: App en P1 con escaneo activo. Datos de prueba: Recibo físico dañado | J16: 1. Apuntar el lector de la T6 a un recibo con código rayado/doblado. 2. Esperar 10 segundos. | K16: No se captura una referencia errónea. Al expirar el tiempo de escaneo se informa que no fue posible leer el código y se ofrece la captura manual. El lector/cámara se libera. | L16: Media | M16: Sin automatizar | N16: No | O16: QA | P16: Manual | Q16: Funcional | S16: =IF($T16<>"Sin Ejecutar", IF($S16="", TODAY(), $S16), "") | T16: Sin Ejecutar
C17: Rompefilas | D17: General | E17: Visualización | F17: CP-AD-ROM-001 | G17: Selección de un adeudo individual | H17: Validar: Selección de un adeudo individual | I17: P2 visible con 4 adeudos (Predial Urbano, Recargos x2, Limpia). Datos de prueba: 1 adeudo — $100.00 | J17: 1. Desplazar (scroll) la lista si es necesario. 2. Tocar la casilla 'PREDIAL URBANO $100.00'. 3. Verificar total actualizado. 4. Presionar 'Pagar ahora'. | K17: La lista es desplazable en la pantalla de la T6, los conceptos y montos no se truncan, el total se actualiza a $100.00 y avanza a P3. | L17: Alta | M17: Sin automatizar | N17: No | O17: QA | P17: Manual | Q17: Funcional | S17: =IF($T17<>"Sin Ejecutar", IF($S17="", TODAY(), $S17), "") | T17: Sin Ejecutar
C18: Rompefilas | D18: General | E18: Visualización | F18: CP-AD-ROM-002 | G18: Selección de todos los adeudos con 'Seleccionar todo' | H18: Validar: Selección de todos los adeudos con 'Seleccionar todo' | I18: P2 visible con 4 adeudos. Datos de prueba: 4 adeudos — Total: $500.00 | J18: 1. Tocar 'Seleccionar todo'. 2. Verificar que los 4 adeudos queden marcados (incluyendo los que quedan fuera de la vista). 3. Presionar 'Pagar ahora'. | K18: Los 4 adeudos quedan marcados, el total = $500.00 MXN es correcto y visible, y avanza a P3. | L18: Alta | M18: Sin automatizar | N18: No | O18: QA | P18: Manual | Q18: Funcional | S18: =IF($T18<>"Sin Ejecutar", IF($S18="", TODAY(), $S18), "") | T18: Sin Ejecutar
C19: Rompefilas | D19: General | E19: Bloqueos | F19: CP-AD-ROM-003 | G19: Intentar avanzar sin seleccionar ningún adeudo | H19: Validar: Intentar avanzar sin seleccionar ningún adeudo | I19: P2 visible. Ninguna casilla marcada. Datos de prueba: 0 adeudos — $0.00 | J19: 1. No tocar ningún adeudo. 2. Presionar 'Pagar ahora'. | K19: El botón 'Pagar ahora' está deshabilitado o se muestra aviso; no se avanza a P3. | L19: Media | M19: Sin automatizar | N19: No | O19: QA | P19: Manual | Q19: Funcional | S19: =IF($T19<>"Sin Ejecutar", IF($S19="", TODAY(), $S19), "") | T19: Sin Ejecutar
C20: Rompefilas | D20: General | E20: Bloqueos | F20: CP-AD-ROM-004 | G20: Cambiar referencia desde P2 ('Cambiar referencia') | H20: Validar: Cambiar referencia desde P2 ('Cambiar referencia') | I20: P2 visible con adeudos cargados. Datos de prueba: Referencia nueva: 9999999999999999 | J20: 1. Presionar 'Cambiar referencia'. 2. Capturar una referencia inválida. 3. Presionar 'Consultar adeudos'. | K20: Se limpian los adeudos del contribuyente anterior y se muestra 'No se encontraron adeudos'. | L20: Media | M20: Sin automatizar | N20: No | O20: QA | P20: Manual | Q20: Funcional | S20: =IF($T20<>"Sin Ejecutar", IF($S20="", TODAY(), $S20), "") | T20: Sin Ejecutar
C21: Rompefilas | D21: General | E21: Visualización | F21: CP-MP-ROM-001 | G21: Selección de método Tarjeta — cobro en la misma T6 | H21: Validar: Selección de método Tarjeta — cobro en la misma T6 | I21: P3 visible. 1 adeudo seleccionado ($100.00). Datos de prueba: Método: Tarjeta | J21: 1. Tocar 'Tarjeta – Débito o crédito'. | K21: La app invoca el módulo de pago integrado de la T6 (sin terminal externa), muestra el monto $100.00 y la instrucción para insertar, deslizar o acercar la tarjeta. | L21: Alta | M21: Sin automatizar | N21: No | O21: QA | P21: Manual | Q21: Funcional | S21: =IF($T21<>"Sin Ejecutar", IF($S21="", TODAY(), $S21), "") | T21: Sin Ejecutar
C22: Rompefilas | D22: Tarjeta | E22: Transacciones | F22: CP-TJ-ROM-001 | G22: Pago con tarjeta de débito con chip — aprobado | H22: Validar: Pago con tarjeta de débito con chip — aprobado | I22: Pantalla de cobro activa en la T6 con monto $100.00. Datos de prueba: Tarjeta débito Visa/Mastercard con fondos | J22: 1. Insertar tarjeta de débito en el lector de chip de la T6. 2. Capturar NIP en la pantalla segura de la T6. 3. Confirmar. | K22: Transacción aprobada. Se regresa a la app y avanza a P5 con confirmación de pago y número de autorización. | L22: Alta | M22: Sin automatizar | N22: No | O22: QA | P22: Manual | Q22: Funcional | S22: =IF($T22<>"Sin Ejecutar", IF($S22="", TODAY(), $S22), "") | T22: Sin Ejecutar
... C76: Rompefilas | D76: General | E76: Visualización | F76: CP-ES-ROM-002 | G76: Tiempo total de atención por contribuyente (rompefilas) | H76: Validar: Tiempo total de atención por contribuyente (rompefilas) | I76: T6 operativa con red estable. Datos de prueba: Flujo completo | J76: 1. Medir desde 'Toque para iniciar' hasta entrega del ticket con escaneo de QR y pago contactless. | K76: Tiempo total ≤ 90 s por contribuyente (objetivo propuesto, ajustar según negocio). | L76: Media | M76: Sin automatizar | N76: No | O76: QA | P76: Manual | Q76: Funcional | S76: =IF($T76<>"Sin Ejecutar", IF($S76="", TODAY(), $S76), "") | T76: Sin Ejecutar
C83: Total de TC´s Ejecutados: | D83: Manual | E83: Automatizado
D84: =COUNTIFS($P$11:$P$76,"Manual",$C$11:$C$76,"<>Selecciona...") -> 65 | E84: =COUNTIFS($P$11:$P$76,"Automatizada",$C$11:$C$76,"<>Selecciona...") -> 0
C85: Total Pasó: | D85: =COUNTIFS($P$11:$P$76,"Manual",$T$11:$T$76,"Pasó",$C$11:$C$76,"<>Selecciona...") -> 0 | E85: =COUNTIFS($P$11:$P$76,"Automatizada",$T$11:$T$76,"Pasó",$C$11:$C$76,"<>Selecciona...") -> 0
C86: Total Falló: | D86: =COUNTIFS($P$11:$P$76,"Manual",$T$11:$T$76,"Falló",$C$11:$C$76,"<>Selecciona...") -> 0 | E86: =COUNTIFS($P$11:$P$76,"Automatizada",$T$11:$T$76,"Falló",$C$11:$C$76,"<>Selecciona...") -> 0
C87: Total Bloqueados: | D87: =COUNTIFS($P$11:$P$76,"Manual",$T$11:$T$76,"Bloqueado",$C$11:$C$76,"<>Selecciona...") -> 0 | E87: =COUNTIFS($P$11:$P$76,"Automatizada",$T$11:$T$76,"Bloqueado",$C$11:$C$76,"<>Selecciona...") -> 0
C88: Total Ejecutados: | D88: =SUM(D85:D87) -> 0 | E88: =SUM(E85:E87) -> 0
C89: Pass Rate: | D89: =IFERROR(D85/D88,0) -> 0 | E89: =IFERROR(E85/E88,0) -> 0
D90: * No eliminar ni modificar Columna B * Los montos y porcentajes se calculan en base a la ejecución
